deepl_fastapi_pw/__init__.py
deepl_fastapi_pw/__main__.py
deepl_fastapi_pw/__main__.py-
deepl_fastapi_pw/deepl_server.py
deepl_fastapi_pw/deepl_server.py.portalocker.lock
deepl_fastapi_pw/deepl_server_async.py
deepl_fastapi_pw/deepl_tr.py
deepl_fastapi_pw/get_pwbrowser.py
deepl_fastapi_pw/run_uvicorn.py
deepl_fastapi_pw/run_uvicorn_async.py
deepl_fastapi_pw-0.1.0a6.dist-info/entry_points.txt
deepl_fastapi_pw-0.1.0a6.dist-info/LICENSE
deepl_fastapi_pw-0.1.0a6.dist-info/METADATA
deepl_fastapi_pw-0.1.0a6.dist-info/WHEEL
deepl_fastapi_pw-0.1.0a6.dist-info/RECORD
