Metadata-Version: 2.1
Name: deepl-fastapi-pw
Version: 0.1.0a6
Summary: deepl via fastapi using playwright
Home-page: https://github.com/ffreemt/deepl-fastapi-playwright
License: MIT
Author: freemt
Requires-Python: >=3.8.3,<4.0.0
Classifier: License :: OSI Approved :: MIT License
Classifier: Programming Language :: Python :: 3
Classifier: Programming Language :: Python :: 3.9
Classifier: Programming Language :: Python :: 3.10
Classifier: Programming Language :: Python :: 3.11
Requires-Dist: about-time (>=4.2.1,<5.0.0)
Requires-Dist: fastapi (>=0.63.0,<0.64.0)
Requires-Dist: get-pwbrowser (>=0.1.1,<0.2.0)
Requires-Dist: get-pwbrowser-sync (>=0.1.3,<0.2.0)
Requires-Dist: logzero (>=1.6.3,<2.0.0)
Requires-Dist: nest-asyncio (>=1.5.6,<2.0.0)
Requires-Dist: playwright (>=1.32.1,<2.0.0)
Requires-Dist: portalocker (>=2.7.0,<3.0.0)
Requires-Dist: pyquery (>=1.4.3,<2.0.0)
Requires-Dist: python-dotenv (>=1.0.0,<2.0.0)
Requires-Dist: uvicorn (>=0.13.4,<0.14.0)
Project-URL: Repository, https://github.com/ffreemt/deepl-fastapi-playwright
